.hgignore
README.txt
setup.cfg
setup.py
collective/__init__.py
collective.chromatable.egg-info/PKG-INFO
collective.chromatable.egg-info/SOURCES.txt
collective.chromatable.egg-info/dependency_links.txt
collective.chromatable.egg-info/entry_points.txt
collective.chromatable.egg-info/namespace_packages.txt
collective.chromatable.egg-info/not-zip-safe
collective.chromatable.egg-info/paster_plugins.txt
collective.chromatable.egg-info/requires.txt
collective.chromatable.egg-info/top_level.txt
collective/chromatable/README.txt
collective/chromatable/__init__.py
collective/chromatable/browser.txt
collective/chromatable/configure.zcml
collective/chromatable/demo.pt
collective/chromatable/interfaces.py
collective/chromatable/tests.py
collective/chromatable/profiles/default/browserlayer.xml
collective/chromatable/profiles/default/cssregistry.xml
collective/chromatable/profiles/default/jsregistry.xml
collective/chromatable/resources/jquery.chromatable.css
collective/chromatable/resources/jquery.chromatable.js
docs/HISTORY.txt
docs/INSTALL.txt
docs/LICENSE.GPL
docs/LICENSE.txt