Metadata-Version: 1.0
Name: collective.chromatable
Version: 1.3.0
Summary: Chromatable JQuery plugin integration for Plone.
Home-page: http://svn.plone.org/svn/collective/
Author: Juan Pablo Giménez
Author-email: jpg@rcom.com.ar
License: GPL
Keywords: jquery plone
Platform: UNKNOWN
Classifier: Framework :: Plone
Classifier: Programming Language :: Python
